Metadata-Version: 1.0
Name: fairdata
Version: 0.0.1
Summary: Automated Time Series in Python
Home-page: https://github.com/firmai/atspy
Author: snowde
Author-email: d.snow@firmai.org
License: MIT
Platform: UNKNOWN
